adept/__init__.py
adept/app.py
adept/globals.py
adept/actor/__init__.py
adept/actor/ac_eval.py
adept/actor/ac_rollout.py
adept/actor/impala.py
adept/actor/base/__init__.py
adept/actor/base/ac_helper.py
adept/actor/base/actor_module.py
adept/agent/__init__.py
adept/agent/actor_critic.py
adept/agent/base/__init__.py
adept/agent/base/agent_module.py
adept/container/__init__.py
adept/container/distrib.py
adept/container/evaluation.py
adept/container/evaluation_thread.py
adept/container/init.py
adept/container/local.py
adept/container/render.py
adept/container/actorlearner/__init__.py
adept/container/actorlearner/learner_container.py
adept/container/actorlearner/rollout_queuer.py
adept/container/actorlearner/rollout_worker.py
adept/container/base/__init__.py
adept/container/base/container.py
adept/container/base/nccl_optimizer.py
adept/env/__init__.py
adept/env/_gym_wrappers.py
adept/env/_spaces.py
adept/env/deepmind_sc2.py
adept/env/openai_gym.py
adept/env/base/__init__.py
adept/env/base/_env.py
adept/env/base/env_module.py
adept/exp/__init__.py
adept/exp/replay.py
adept/exp/rollout.py
adept/exp/base/__init__.py
adept/exp/base/exp_module.py
adept/exp/base/spec_builder.py
adept/learner/__init__.py
adept/learner/ac_rollout.py
adept/learner/impala.py
adept/learner/base/__init__.py
adept/learner/base/dm_return_scale.py
adept/learner/base/learner_module.py
adept/manager/__init__.py
adept/manager/simple_env_manager.py
adept/manager/subproc_env_manager.py
adept/manager/base/__init__.py
adept/manager/base/manager_module.py
adept/modules/__init__.py
adept/modules/attention.py
adept/modules/memory.py
adept/modules/mlp.py
adept/modules/norm.py
adept/modules/sequence.py
adept/modules/spatial.py
adept/network/__init__.py
adept/network/modular_network.py
adept/network/base/__init__.py
adept/network/base/base.py
adept/network/base/network_module.py
adept/network/base/submodule.py
adept/network/net1d/__init__.py
adept/network/net1d/identity_1d.py
adept/network/net1d/linear.py
adeptRL-0.2.0.dist-info/LICENSE
adeptRL-0.2.0.dist-info/METADATA
adeptRL-0.2.0.dist-info/WHEEL
adeptRL-0.2.0.dist-info/top_level.txt
adeptRL-0.2.0.dist-info/RECORD
