Metadata-Version: 2.1
Name: adeptRL
Version: 0.2.0
Summary: Reinforcement Learning Framework
Home-page: https://github.com/heronsystems/adeptRL
Author: heron
Author-email: adept@heronsystems.com
License: GNU
Platform: UNKNOWN
Requires-Python: >=3.5.0
Requires-Dist: numpy (>=1.14)
Requires-Dist: gym[atari] (>=0.10)
Requires-Dist: absl-py (>=0.2)
Requires-Dist: tensorboard (>=1.14)
Requires-Dist: cloudpickle (>=0.5)
Requires-Dist: opencv-python-headless (>=3.4)
Requires-Dist: pyzmq (>=17.1.2)
Requires-Dist: docopt (>=0.6)
Requires-Dist: torch (>=1.3.1)
Requires-Dist: torchvision (>=0.4.2)
Provides-Extra: all
Requires-Dist: mpi4py (>=3.0) ; extra == 'all'
Requires-Dist: pysc2 (>=2.0) ; extra == 'all'
Requires-Dist: pyinstrument (>=2.0) ; extra == 'all'
Requires-Dist: pytest ; extra == 'all'
Provides-Extra: mpi
Requires-Dist: mpi4py (>=3.0) ; extra == 'mpi'
Provides-Extra: profiler
Requires-Dist: pyinstrument (>=2.0) ; extra == 'profiler'
Provides-Extra: sc2
Requires-Dist: pysc2 (>=2.0) ; extra == 'sc2'
